{
  "title": {
    "zh": "网格热力图",
    "en": "heatmap"
  },
  "demos": [
    {
      "filename": "grid_world.js",
      "title": "网格世界地图",
      "screenshot":"https://gw.alipayobjects.com/mdn/rms_23a451/afts/img/A*1PeGSboLGUUAAAAAAAAAAABkARQnAQ"
    },
    {
      "filename": "china.js",
      "title": "网格热力图",
      "screenshot":"https://gw.alipayobjects.com/mdn/antv_site/afts/img/A*XPBuSIPPgsgAAAAAAAAAAABkARQnAQ"
    },
    {
      "filename": "grid1.js",
      "title": "",
      "screenshot":"https://gw.alipayobjects.com/mdn/antv_site/afts/img/A*Uo9oQolgoxYAAAAAAAAAAABkARQnAQ"

    },
    {
      "filename": "heatmap3.js",
      "title": "网格布局 圆形",
      "screenshot":"https://gw.alipayobjects.com/mdn/antv_site/afts/img/A*Ucz6SJ5wU_0AAAAAAAAAAABkARQnAQ"

    },
    {
      "filename": "world.js",
      "title": "网格热力图",
      "screenshot":"https://gw.alipayobjects.com/mdn/antv_site/afts/img/A*f1IDQ7AG-00AAAAAAAAAAABkARQnAQ"

    }

  ]
}
