{
  "title": {
    "zh": "图库",
    "en": "Gallery"
  },
  "demos": [
    {
      "filename": "province_map.ts",
      "title": "福建省地图",
      "new": true,
      "screenshot": "https://mdn.alipayobjects.com/huamei_qa8qxu/afts/img/A*HyCxTKbk-lsAAAAAAAAAAAAADmJ7AQ/original"
    },
    {
      "filename": "column_dark.js",
      "title": "3D柱图深色",
      "screenshot": "https://gw.alipayobjects.com/mdn/rms_816329/afts/img/A*FGjMT4CenkkAAAAAAAAAAAAAARQnAQ"
    },
    {
      "filename": "arc-circle.js",
      "title": "弧线地图",
      "screenshot": "https://gw.alipayobjects.com/mdn/rms_816329/afts/img/A*hX_VQ5q77xMAAAAAAAAAAAAAARQnAQ"
    },
    {
      "filename": "bus_dark.js",
      "title": "公交线路深色",
      "screenshot": "https://gw.alipayobjects.com/mdn/rms_816329/afts/img/A*cvU2R7WFfeAAAAAAAAAAAAAAARQnAQ"
    },
    {
      "filename": "light.js",
      "title": "蜂窝图3D",
      "screenshot": "https://gw.alipayobjects.com/mdn/rms_816329/afts/img/A*PtMUR6hsN9EAAAAAAAAAAAAAARQnAQ"
    },
    {
      "filename": "swipe.ts",
      "title": "卷帘对比-作物长势",
      "new": true,
      "screenshot": "https://mdn.alipayobjects.com/huamei_qa8qxu/afts/img/A*b1WCRJjht2wAAAAAAAAAAAAADmJ7AQ/original"
    },
    {
      "filename": "normal.js",
      "title": "亮度图",
      "screenshot": "https://gw.alipayobjects.com/mdn/rms_816329/afts/img/A*qI2gRo_w0XoAAAAAAAAAAAAAARQnAQ"
    }
  ]
}
